wpyscan/__init__.py
wpyscan/exploit_grabber.py
wpyscan/wprecon.py
wpyscan-1.0.1.data/scripts/wpyscan
wpyscan-1.0.1.dist-info/METADATA
wpyscan-1.0.1.dist-info/WHEEL
wpyscan-1.0.1.dist-info/top_level.txt
wpyscan-1.0.1.dist-info/RECORD
