Metadata-Version: 2.1
Name: wpyscan
Version: 1.0.1
Summary: Wordpress pentest tool
Home-page: https://github.com/hmikihth/wpyscan
Author: ganapati (@G4N4P4T1), Miklos Horvath (hmikihth)
Maintainer: Miklos Horvath <hmiki@blackpantheros.eu>
License: BEER-WARE
Platform: UNKNOWN
Classifier: Development Status :: 5 - Production/Stable
Classifier: Intended Audience :: System Administrators
Classifier: Topic :: Utilities
Classifier: Operating System :: POSIX :: Linux
Classifier: Operating System :: POSIX :: BSD :: FreeBSD
Classifier: Operating System :: POSIX :: BSD :: OpenBSD
Classifier: Programming Language :: Python :: 3
Classifier: Programming Language :: Python :: 3.3
Classifier: Programming Language :: Python :: 3.4
Classifier: Programming Language :: Python :: 3.5
Classifier: Programming Language :: Python :: 3.6
Classifier: Programming Language :: Python :: 3.7
